Workbook
Name VAT: Settings!$B$1
Name OrderProducts: Orders!$A$2:$A$7
Name Discount: 0.05

Sheet Orders
A1: Product | B1: Quantity | C1: Price | D1: Total | E1: Category | G1: Doubled
A2: Widget | B2: 120 | C2: 9.99 | D2: =B2*C2 | E2: Hardware | G2: {=B2:B7*2}
A3: Gadget | B3: 45 | C3: 24.5 | D3: =B3*C3 | E3: Hardware
A4: Gizmo | B4: 80 | C4: 14.25 | D4: =B4*C4 | E4: Hardware
A5: Support plan | B5: 12 | C5: 199 | D5: =B5*C5 | E5: Services
A6: Training | B6: 5 | C6: 450 | D6: =B6*C6 | E6: Services
A7: Консультація | B7: 3 | C7: 1200 | D7: =B7*C7 | E7: Послуги
A8: Sum | D8: =SUM(D2:D7)
A9: Average price | D9: =AVERAGE(C2:C7)
A10: With VAT | D10: =D8*(1+VAT)
A11: Hardware total | D11: =SUMIFS(D2:D7,E2:E7,"Hardware")
A12: Orders over 1000 | D12: =COUNTIF(D2:D7,">1000")
A14: Documentation
A15: Go to the summary

Sheet Lookup
A1: Product | B1: Found price | C1: Row | D1: Label | E1: Due
A2: Widget | B2: =VLOOKUP(A2,Orders!$A$2:$C$7,3,FALSE) | C2: =MATCH(A2,Orders!$A$2:$A$7,0) | D2: =UPPER(LEFT(A2,3))&"-"&TEXT(B2,"0.00") | E2: =EDATE(DATE(2026,1,31),ROW()-1)
A3: Gadget | B3: =VLOOKUP(A3,Orders!$A$2:$C$7,3,FALSE) | C3: =MATCH(A3,Orders!$A$2:$A$7,0) | D3: =UPPER(LEFT(A3,3))&"-"&TEXT(B3,"0.00") | E3: =EDATE(DATE(2026,1,31),ROW()-1)
A4: Gizmo | B4: =VLOOKUP(A4,Orders!$A$2:$C$7,3,FALSE) | C4: =MATCH(A4,Orders!$A$2:$A$7,0) | D4: =UPPER(LEFT(A4,3))&"-"&TEXT(B4,"0.00") | E4: =EDATE(DATE(2026,1,31),ROW()-1)
A5: Support plan | B5: =VLOOKUP(A5,Orders!$A$2:$C$7,3,FALSE) | C5: =MATCH(A5,Orders!$A$2:$A$7,0) | D5: =UPPER(LEFT(A5,3))&"-"&TEXT(B5,"0.00") | E5: =EDATE(DATE(2026,1,31),ROW()-1)
A7: Safe division | B7: =IFERROR(1/0,"n/a")
A8: Index/match | B8: =INDEX(Orders!$D$2:$D$7,MATCH("Gadget",Orders!$A$2:$A$7,0))
A9: Discount (sheet name) | B9: =Discount

Sheet Jan
A1: Amount | B1: 100

Sheet Feb
A1: Amount | B1: 150

Sheet Mar
A1: Amount | B1: 125

Sheet Budget
A1: Quarter | B1: =SUM(Jan:Mar!B1)
A3: Item | B3: Plan | C3: Actual | D3: Delta
A4: Rent | B4: 1000 | C4: 1000 | D4: =BudgetTable[[#This Row],[Actual]]-BudgetTable[[#This Row],[Plan]]
A5: Staff | B5: 5000 | C5: 5200 | D5: =BudgetTable[[#This Row],[Actual]]-BudgetTable[[#This Row],[Plan]]
A6: Travel | B6: 800 | C6: 650 | D6: =BudgetTable[[#This Row],[Actual]]-BudgetTable[[#This Row],[Plan]]
A7: Total | B7: =SUBTOTAL(109,BudgetTable[Plan]) | C7: =SUBTOTAL(109,BudgetTable[Actual]) | D7: =SUBTOTAL(109,BudgetTable[Delta])

Sheet Settings
A1: VAT | B1: 0.2

Sheet Summary
A1: Orders total | B1: =Orders!D8
A2: Largest order | B2: =MAX(Orders!D2:D7)
A3: Products | B3: =COUNTA(OrderProducts)
A4: Table total | B4: =SUM(OrderList[Total])
A5: Quarter budget | B5: =Budget!B1
